{"from":{"departureAirportIata":"VBY","departureAirportIcao":"ESSV","departureAirportSwedish":"Visby","departureAirportEnglish":"Visby","flightDepartureDate":"2023-07-08"},"numberOfFlights":13,"flights":[{"flightId":"SK078","arrivalAirportSwedish":"Stockholm ARN","arrivalAirportEnglish":"Stockholm ARN","airlineOperator":{"iata":"SK","icao":"SAS","name":"SAS Scandinavian Airlines"},"departureTime":{"scheduledUtc":"2023-07-08T07:35:00Z"},"locationAndStatus":{"terminal":"T1","flightLegStatus":"DEL","flightLegStatusSwedish":"Borttagen","flightLegStatusEnglish":"Deleted"},"checkIn":{},"codeShareData":[],"flightLegIdentifier":{"callsign":"SAS078","flightId":"SK078","flightDepartureDateUtc":"2023-07-08T00:00:00Z","departureAirportIata":"VBY","arrivalAirportIata":"ARN","departureAirportIcao":"ESSV","arrivalAirportIcao":"ESSA"},"viaDestinations":[],"remarksEnglish":[],"remarksSwedish":[],"diIndicator":"D"},{"flightId":"TF449","arrivalAirportSwedish":"Stockholm BMA","arrivalAirportEnglish":"Stockholm BMA","airlineOperator":{"iata":"TF","icao":"BRX","name":"BRA"},"departureTime":{"scheduledUtc":"2023-07-08T12:50:00Z"},"locationAndStatus":{"terminal":"T1","flightLegStatus":"DEL","flightLegStatusSwedish":"Borttagen","flightLegStatusEnglish":"Deleted"},"checkIn":{},"codeShareData":[],"flightLegIdentifier":{"callsign":"BRX449","flightId":"TF449","flightDepartureDateUtc":"2023-07-08T00:00:00Z","departureAirportIata":"VBY","arrivalAirportIata":"BMA","departureAirportIcao":"ESSV","arrivalAirportIcao":"ESSB"},"viaDestinations":[],"remarksEnglish":[],"remarksSwedish":[],"diIndicator":"D"},{"flightId":"XX821","arrivalAirportSwedish":"Guernsey","arrivalAirportEnglish":"Guernsey","airlineOperator":{"iata":"XX","icao":"XX","name":"Score Dummy Operator"},"departureTime":{"scheduledUtc":"2023-07-08T09:30:00Z"},"locationAndStatus":{"terminal":"T1","flightLegStatus":"DEL","flightLegStatusSwedish":"Borttagen","flightLegStatusEnglish":"Deleted"},"checkIn":{},"codeShareData":[],"flightLegIdentifier":{"callsign":"XX821","aircraftRegistration":"GNSEY","flightId":"XX821","flightDepartureDateUtc":"2023-07-08T00:00:00Z","departureAirportIata":"VBY","arrivalAirportIata":"GCI","departureAirportIcao":"ESSV","arrivalAirportIcao":"EGJB"},"viaDestinations":[],"remarksEnglish":[],"remarksSwedish":[],"diIndicator":"I"},{"flightId":"GR821","arrivalAirportSwedish":"Guernsey","arrivalAirportEnglish":"Guernsey","airlineOperator":{"iata":"GR","icao":"AUR","name":"AURIGNY AIR SERVICES"},"departureTime":{"scheduledUtc":"2023-07-08T09:30:00Z"},"locationAndStatus":{"terminal":"T1","flightLegStatus":"SCH","flightLegStatusSwedish":"Planerad","flightLegStatusEnglish":"Scheduled"},"checkIn":{},"codeShareData":[],"flightLegIdentifier":{"callsign":"AUR821","flightId":"GR821","flightDepartureDateUtc":"2023-07-08T00:00:00Z","departureAirportIata":"VBY","arrivalAirportIata":"GCI","departureAirportIcao":"ESSV","arrivalAirportIcao":"EGJB"},"viaDestinations":[],"remarksEnglish":[],"remarksSwedish":[],"diIndicator":"I"},{"flightId":"XHGR821","arrivalAirportSwedish":"Guernsey","arrivalAirportEnglish":"Guernsey","airlineOperator":{"iata":"XH","icao":"XH","name":"Private Flights"},"departureTime":{"scheduledUtc":"2023-07-08T09:30:00Z"},"locationAndStatus":{"terminal":"T1","flightLegStatus":"DEL","flightLegStatusSwedish":"Borttagen","flightLegStatusEnglish":"Deleted"},"checkIn":{},"codeShareData":[],"flightLegIdentifier":{"callsign":"XHGR821","aircraftRegistration":"GNSEY","flightId":"XHGR821","flightDepartureDateUtc":"2023-07-08T00:00:00Z","departureAirportIata":"VBY","arrivalAirportIata":"GCI","departureAirportIcao":"ESSV","arrivalAirportIcao":"EGJB"},"viaDestinations":[],"remarksEnglish":[],"remarksSwedish":[],"diIndicator":"I"},{"flightId":"TF441","arrivalAirportSwedish":"Stockholm BMA","arrivalAirportEnglish":"Stockholm BMA","airlineOperator":{"iata":"TF","icao":"BRX","name":"BRA"},"departureTime":{"scheduledUtc":"2023-07-08T06:20:00Z"},"locationAndStatus":{"terminal":"T1","flightLegStatus":"SCH","flightLegStatusSwedish":"Planerad","flightLegStatusEnglish":"Scheduled"},"checkIn":{},"codeShareData":[],"flightLegIdentifier":{"callsign":"BRX441","flightId":"TF441","flightDepartureDateUtc":"2023-07-08T00:00:00Z","departureAirportIata":"VBY","arrivalAirportIata":"BMA","departureAirportIcao":"ESSV","arrivalAirportIcao":"ESSB"},"viaDestinations":[],"remarksEnglish":[],"remarksSwedish":[],"diIndicator":"D"},{"flightId":"AY882","arrivalAirportSwedish":"Helsingfors","arrivalAirportEnglish":"Helsinki","airlineOperator":{"iata":"AY","icao":"FIN","name":"Finnair"},"departureTime":{"scheduledUtc":"2023-07-08T06:25:00Z"},"locationAndStatus":{"terminal":"T1","flightLegStatus":"SCH","flightLegStatusSwedish":"Planerad","flightLegStatusEnglish":"Scheduled"},"checkIn":{},"codeShareData":[],"flightLegIdentifier":{"callsign":"FIN882","flightId":"AY882","flightDepartureDateUtc":"2023-07-08T00:00:00Z","departureAirportIata":"VBY","arrivalAirportIata":"HEL","departureAirportIcao":"ESSV","arrivalAirportIcao":"EFHK"},"viaDestinations":[],"remarksEnglish":[],"remarksSwedish":[],"diIndicator":"S"},{"flightId":"TF1150","arrivalAirportSwedish":"Göteborg","arrivalAirportEnglish":"Göteborg","airlineOperator":{"iata":"TF","icao":"BRX","name":"BRA"},"departureTime":{"scheduledUtc":"2023-07-08T08:40:00Z"},"locationAndStatus":{"terminal":"T1","flightLegStatus":"SCH","flightLegStatusSwedish":"Planerad","flightLegStatusEnglish":"Scheduled"},"checkIn":{},"codeShareData":[],"flightLegIdentifier":{"callsign":"BRX15Z","flightId":"TF1150","flightDepartureDateUtc":"2023-07-08T00:00:00Z","departureAirportIata":"VBY","arrivalAirportIata":"GOT","departureAirportIcao":"ESSV","arrivalAirportIcao":"ESGG"},"viaDestinations":[],"remarksEnglish":[],"remarksSwedish":[],"diIndicator":"D"},{"flightId":"FR7596","arrivalAirportSwedish":"Stockholm ARN","arrivalAirportEnglish":"Stockholm ARN","airlineOperator":{"iata":"FR","icao":"RYR","name":"Ryanair Ltd"},"departureTime":{"scheduledUtc":"2023-07-08T06:30:00Z"},"locationAndStatus":{"terminal":"T1","flightLegStatus":"SCH","flightLegStatusSwedish":"Planerad","flightLegStatusEnglish":"Scheduled"},"checkIn":{},"codeShareData":[],"flightLegIdentifier":{"callsign":"RYR7596","flightId":"FR7596","flightDepartureDateUtc":"2023-07-08T00:00:00Z","departureAirportIata":"VBY","arrivalAirportIata":"ARN","departureAirportIcao":"ESSV","arrivalAirportIcao":"ESSA"},"viaDestinations":[],"remarksEnglish":[],"remarksSwedish":[],"diIndicator":"D"},{"flightId":"SK080","arrivalAirportSwedish":"Stockholm ARN","arrivalAirportEnglish":"Stockholm ARN","airlineOperator":{"iata":"SK","icao":"SAS","name":"SAS Scandinavian Airlines"},"departureTime":{"scheduledUtc":"2023-07-08T07:50:00Z"},"locationAndStatus":{"terminal":"T1","flightLegStatus":"SCH","flightLegStatusSwedish":"Planerad","flightLegStatusEnglish":"Scheduled"},"checkIn":{},"codeShareData":[],"flightLegIdentifier":{"callsign":"SAS080","flightId":"SK080","flightDepartureDateUtc":"2023-07-08T00:00:00Z","departureAirportIata":"VBY","arrivalAirportIata":"ARN","departureAirportIcao":"ESSV","arrivalAirportIcao":"ESSA"},"viaDestinations":[],"remarksEnglish":[],"remarksSwedish":[],"diIndicator":"D"},{"flightId":"TF443","arrivalAirportSwedish":"Stockholm BMA","arrivalAirportEnglish":"Stockholm BMA","airlineOperator":{"iata":"TF","icao":"BRX","name":"BRA"},"departureTime":{"scheduledUtc":"2023-07-08T11:50:00Z"},"locationAndStatus":{"terminal":"T1","flightLegStatus":"SCH","flightLegStatusSwedish":"Planerad","flightLegStatusEnglish":"Scheduled"},"checkIn":{},"codeShareData":[],"flightLegIdentifier":{"callsign":"BRX443","flightId":"TF443","flightDepartureDateUtc":"2023-07-08T00:00:00Z","departureAirportIata":"VBY","arrivalAirportIata":"BMA","departureAirportIcao":"ESSV","arrivalAirportIcao":"ESSB"},"viaDestinations":[],"remarksEnglish":[],"remarksSwedish":[],"diIndicator":"D"},{"flightId":"TF445","arrivalAirportSwedish":"Stockholm BMA","arrivalAirportEnglish":"Stockholm BMA","airlineOperator":{"iata":"TF","icao":"BRX","name":"BRA"},"departureTime":{"scheduledUtc":"2023-07-08T12:35:00Z"},"locationAndStatus":{"terminal":"T1","flightLegStatus":"SCH","flightLegStatusSwedish":"Planerad","flightLegStatusEnglish":"Scheduled"},"checkIn":{},"codeShareData":[],"flightLegIdentifier":{"callsign":"BRX445","flightId":"TF445","flightDepartureDateUtc":"2023-07-08T00:00:00Z","departureAirportIata":"VBY","arrivalAirportIata":"BMA","departureAirportIcao":"ESSV","arrivalAirportIcao":"ESSB"},"viaDestinations":[],"remarksEnglish":[],"remarksSwedish":[],"diIndicator":"D"},{"flightId":"SK082","arrivalAirportSwedish":"Stockholm ARN","arrivalAirportEnglish":"Stockholm ARN","airlineOperator":{"iata":"SK","icao":"SAS","name":"SAS Scandinavian Airlines"},"departureTime":{"scheduledUtc":"2023-07-08T14:20:00Z"},"locationAndStatus":{"terminal":"T1","flightLegStatus":"SCH","flightLegStatusSwedish":"Planerad","flightLegStatusEnglish":"Scheduled"},"checkIn":{},"codeShareData":["TK8241"],"flightLegIdentifier":{"callsign":"SAS082","aircraftRegistration":"ESATC","flightId":"SK082","flightDepartureDateUtc":"2023-07-08T00:00:00Z","departureAirportIata":"VBY","arrivalAirportIata":"ARN","departureAirportIcao":"ESSV","arrivalAirportIcao":"ESSA"},"viaDestinations":[],"remarksEnglish":[],"remarksSwedish":[],"diIndicator":"D"}]}